nib_save_wrapper/__init__.py
nib_save_wrapper/nib_save_wrapper.py
nib_save_wrapper-0.2.0.dist-info/WHEEL
nib_save_wrapper-0.2.0.dist-info/METADATA
nib_save_wrapper-0.2.0.dist-info/RECORD
